Metadata-Version: 1.1
Name: target-parquet
Version: 0.0.1
Summary: Singer.io target for writing into parquet files
Home-page: https://singer.io
Author: Stitch
Author-email: UNKNOWN
License: UNKNOWN
Platform: UNKNOWN
Classifier: Programming Language :: Python :: 3 :: Only
